pysunergy_calc/__init__.py
pysunergy_calc-1.0.4.dist-info/METADATA
pysunergy_calc-1.0.4.dist-info/WHEEL
pysunergy_calc-1.0.4.dist-info/licenses/LICENSE
pysunergy_calc-1.0.4.dist-info/RECORD
