Metadata-Version: 2.4
Name: pysunergy_calc
Version: 1.0.4
Summary: Geometry-based solar potential, irradiance, and solar PV energy calculations in Python without external APIs.
Project-URL: Homepage, https://github.com/abdullahwaqar/pysunergy_calc
Project-URL: Repository, https://github.com/abdullahwaqar/pysunergy_calc
Author: Abdullah Waqar
License: MIT
License-File: LICENSE
Keywords: PV output calculation,cleantech,energy modeling,engineering,geometry,math,no API,photovoltaic,pv,pv system,renewable energy,solar,solar energy,solar insolation,solar irradiance,solar panel,solar potential,solar power,sun position
Requires-Python: >=3.7
Provides-Extra: dev
Requires-Dist: pytest; extra == 'dev'
Requires-Dist: ruff; extra == 'dev'
